dlqhandler/__init__.py
dlqhandler/dataprovider/__init__.py
dlqhandler/dataprovider/send_to_aws_sqs.py
dlqhandler/dataprovider/sqs_queue.py
dlqhandler/services/__init__.py
dlqhandler/services/cloudwatch.py
dlqhandler/services/process.py
dlqhandler-0.8.0.dist-info/LICENSE
dlqhandler-0.8.0.dist-info/METADATA
dlqhandler-0.8.0.dist-info/WHEEL
dlqhandler-0.8.0.dist-info/top_level.txt
dlqhandler-0.8.0.dist-info/RECORD
