Metadata-Version: 2.1
Name: dlqhandler
Version: 0.8.0
Summary: A library for handling DLQ messages in AWS SQS
Home-page: https://github.com/seuusuario/dlq_handler_lib
Author: Marcelo Ferreira
Author-email: jaytilangus@gmail.com
License: UNKNOWN
Platform: UNKNOWN
Classifier: Programming Language :: Python :: 3
Classifier: License :: OSI Approved :: MIT License
Classifier: Operating System :: OS Independent
Requires-Python: >=3.6
License-File: LICENSE
Requires-Dist: boto3
Requires-Dist: mock
